muvera-0.2.0.dist-info/METADATA
muvera-0.2.0.dist-info/WHEEL
muvera-0.2.0.dist-info/licenses/LICENSE
muvera/__init__.py
muvera/muvera.cp312-win_amd64.pyd
muvera-0.2.0.dist-info/RECORD
