Metadata-Version: 2.4
Name: muvera
Version: 0.2.0
Classifier: Development Status :: 4 - Beta
Classifier: Intended Audience :: Developers
Classifier: Intended Audience :: Science/Research
Classifier: License :: OSI Approved :: MIT License
Classifier: Programming Language :: Python :: 3
Classifier: Programming Language :: Python :: 3.8
Classifier: Programming Language :: Python :: 3.9
Classifier: Programming Language :: Python :: 3.10
Classifier: Programming Language :: Python :: 3.11
Classifier: Programming Language :: Python :: 3.12
Classifier: Topic :: Scientific/Engineering :: Artificial Intelligence
Classifier: Topic :: Scientific/Engineering :: Information Analysis
Requires-Dist: numpy>=1.20.0
Requires-Dist: cffi>=1.0.0
Requires-Dist: pytest>=7.0.0 ; extra == 'dev'
Requires-Dist: black>=22.0.0 ; extra == 'dev'
Requires-Dist: mypy>=1.0.0 ; extra == 'dev'
Provides-Extra: dev
License-File: LICENSE
Summary: An unofficial Rust implementation of MuVERA: Multi-Vector Retrieval via Fixed Dimensional Encodings
Keywords: muvera,multi-vector,embedding,fde,retrieval
Home-Page: https://github.com/NewBornRustacean/muvera-rs
Author: NewBornRustacean <huiseomkim@gmail.com>
Author-email: NewBornRustacean <huiseomkim@gmail.com>
License: MIT
Requires-Python: >=3.8
Project-URL: Homepage, https://github.com/NewBornRustacean/muvera-rs
Project-URL: Repository, https://github.com/NewBornRustacean/muvera-rs
Project-URL: Documentation, https://docs.rs/muvera-rs
Project-URL: Issues, https://github.com/NewBornRustacean/muvera-rs/issues
